image_processing_img/__init__.py
image_processing_img/processing/__init__.py
image_processing_img/processing/combination.py
image_processing_img/processing/transfomation.py
image_processing_img/utils/__init__.py
image_processing_img/utils/io.py
image_processing_img/utils/plot.py
image_processing_img-0.0.3.dist-info/METADATA
image_processing_img-0.0.3.dist-info/WHEEL
image_processing_img-0.0.3.dist-info/top_level.txt
image_processing_img-0.0.3.dist-info/RECORD
