Metadata-Version: 2.1
Name: image-processing-img
Version: 0.0.3
Summary: My short description
Home-page: https://github.com/FlaysonSantos/
Author: Flayson Junio Pereira Santos
Author-email: flaysonemail@gmail.com
Requires-Python: >=3.8
